ntxbuild/__init__.py
ntxbuild/_version.py
ntxbuild/build.py
ntxbuild/cli.py
ntxbuild/config.py
ntxbuild/env_data.py
ntxbuild/setup.py
ntxbuild/toolchains.ini
ntxbuild/toolchains.py
ntxbuild/utils.py
ntxbuild-0.4.0.dist-info/licenses/LICENSE
ntxbuild-0.4.0.dist-info/METADATA
ntxbuild-0.4.0.dist-info/WHEEL
ntxbuild-0.4.0.dist-info/entry_points.txt
ntxbuild-0.4.0.dist-info/top_level.txt
ntxbuild-0.4.0.dist-info/RECORD
